unicor/__init__.py
unicor/unicor_metric.py
unicor/unicorp.py
unicor-0.2.0.dist-info/licenses/LICENSE
unicor-0.2.0.dist-info/METADATA
unicor-0.2.0.dist-info/WHEEL
unicor-0.2.0.dist-info/top_level.txt
unicor-0.2.0.dist-info/RECORD
