Metadata-Version: 2.4
Name: unicor
Version: 0.2.0
Summary: Hierarchical Feature Selection through Propagation of Uniquely Correlated Entities
Author-email: Sebastian Staab <sebastian.staab@uni-konstanz.de>
License: MIT
Project-URL: Homepage, https://github.com/SebastianStaab/UniCor
Project-URL: Issues, https://github.com/SebastianStaab/UniCor/issues
Classifier: Programming Language :: Python :: 3
Classifier: License :: OSI Approved :: MIT License
Classifier: Operating System :: OS Independent
Requires-Python: >=3.9
License-File: LICENSE
Dynamic: license-file
